exasol/ai/mcp/server/db_connection.py
exasol/ai/mcp/server/keyword_search.py
exasol/ai/mcp/server/main.py
exasol/ai/mcp/server/mcp_server.py
exasol/ai/mcp/server/meta_query.py
exasol/ai/mcp/server/parameter_parser.py
exasol/ai/mcp/server/parameter_pattern.py
exasol/ai/mcp/server/server_settings.py
exasol/ai/mcp/server/text_to_sql_option/e_r_diagram.py
exasol/ai/mcp/server/text_to_sql_option/images/langgraph_workflow.png
exasol/ai/mcp/server/text_to_sql_option/images/sql_history.png
exasol/ai/mcp/server/text_to_sql_option/intro/intro.py
exasol/ai/mcp/server/text_to_sql_option/resources/__init__.py
exasol/ai/mcp/server/text_to_sql_option/resources/result_rendering_prompt.txt
exasol/ai/mcp/server/text_to_sql_option/resources/sql_translation_prompt.txt
exasol/ai/mcp/server/text_to_sql_option/secondary_nodes/info_messages_llm.py
exasol/ai/mcp/server/text_to_sql_option/secondary_nodes/routing.py
exasol/ai/mcp/server/text_to_sql_option/sql_history.py
exasol/ai/mcp/server/text_to_sql_option/text_to_sql.py
exasol/ai/mcp/server/text_to_sql_option/utilities/__init__.py
exasol/ai/mcp/server/text_to_sql_option/utilities/database_functions.py
exasol/ai/mcp/server/text_to_sql_option/utilities/helpers.py
exasol/ai/mcp/server/text_to_sql_option/utilities/llm.py
exasol/ai/mcp/server/text_to_sql_option/utilities/load_prompts.py
exasol/ai/mcp/server/version.py
exasol_mcp_server_governed_sql-1.0.0.dist-info/METADATA
exasol_mcp_server_governed_sql-1.0.0.dist-info/WHEEL
exasol_mcp_server_governed_sql-1.0.0.dist-info/entry_points.txt
exasol_mcp_server_governed_sql-1.0.0.dist-info/licenses/LICENSE
exasol_mcp_server_governed_sql-1.0.0.dist-info/RECORD
