Metadata-Version: 2.4
Name: exasol-mcp-server-governed-sql
Version: 1.0.0
Summary: Exasol MCP Server with a experimental text-to-SQL option.
License-Expression: MIT
License-File: LICENSE
Keywords: exasol,MCP server,Text-to-SQL
Author: Dirk Beerbohm (Text-to-SQL)
Author-email: dirk.beerbohm@exasol.com
Requires-Python: >=3.10,<=3.13
Classifier: Programming Language :: Python :: 3
Classifier: Programming Language :: Python :: 3.10
Classifier: Programming Language :: Python :: 3.11
Classifier: Programming Language :: Python :: 3.12
Classifier: Programming Language :: Python :: 3.13
Requires-Dist: chromadb (>=1.0.20)
Requires-Dist: cryptography (>=45.0.7)
Requires-Dist: fastmcp (>=2.12.2)
Requires-Dist: langchain (>=0.3.27)
Requires-Dist: langchain-openai (>=0.3.32)
Requires-Dist: langgraph (>=0.6.7)
Requires-Dist: loguru (>=0.7.3)
Requires-Dist: pyexasol (>=1.1.0)
Requires-Dist: rank-bm25 (>=0.2.2)
Requires-Dist: sql-formatter (>=0.6.2)
Requires-Dist: sqlglot (>=27.13.2)
Requires-Dist: stopwords (>=1.0.2)
